pyprediktorutilities/__init__.py
pyprediktorutilities/file_transfer.py
pyprediktorutilities/send_email.py
pyprediktorutilities/shared.py
pyprediktorutilities/singleton.py
pyprediktorutilities/templating.py
pyprediktorutilities/dwh/__init__.py
pyprediktorutilities/dwh/dwh.py
pyprediktorutilities/dwh/dwh_singleton.py
pyPrediktorUtilities-0.4.9.dist-info/LICENSE.txt
pyPrediktorUtilities-0.4.9.dist-info/METADATA
pyPrediktorUtilities-0.4.9.dist-info/WHEEL
pyPrediktorUtilities-0.4.9.dist-info/top_level.txt
pyPrediktorUtilities-0.4.9.dist-info/RECORD
