Metadata-Version: 2.2
Name: pyPrediktorUtilities
Version: 0.4.9
Summary: Helper functions for Prediktor projects
Home-page: https://github.com/PrediktorAS/pyPrediktorUtilities
Author: Prediktor
Author-email: support@prediktor.com
License: MIT
Project-URL: Documentation, https://prediktoras.github.io/pyPrediktorUtilities/
Project-URL: Source, https://github.com/PrediktorAS/pyPrediktorUtilities
Project-URL: Changelog, https://github.com/PrediktorAS/pyPrediktorUtilities/releases
Project-URL: Tracker, https://github.com/PrediktorAS/pyPrediktorUtilities/issues
Platform: any
Classifier: Development Status :: 4 - Beta
Classifier: Programming Language :: Python
Requires-Python: >=3.9
License-File: LICENSE.txt
Requires-Dist: importlib-metadata; python_version < "3.9"
Requires-Dist: requests<3.0,>=2.28.1
Requires-Dist: pydantic<3.0,>=2.0
Requires-Dist: email-validator<3.0,>=2.0.0
Requires-Dist: paramiko<4.0,>=3.3.1
Requires-Dist: jinja2<4.0,>=3.0.1
Requires-Dist: pandas<3.0,>=1.4.4
Requires-Dist: pyodbc<6.0.0
Provides-Extra: testing
Requires-Dist: setuptools<76.0.0; extra == "testing"
Requires-Dist: pytest<9.0.0; extra == "testing"
Requires-Dist: pytest-cov<6.0.0; extra == "testing"
Requires-Dist: pytest-mock<4.0.0; extra == "testing"
Requires-Dist: pyarrow<17.0.0; extra == "testing"
